setup.py
django_alt/__init__.py
django_alt/dotdict.py
django_alt/endpoints.py
django_alt/managers.py
django_alt/serializers.py
django_alt.egg-info/PKG-INFO
django_alt.egg-info/SOURCES.txt
django_alt.egg-info/dependency_links.txt
django_alt.egg-info/requires.txt
django_alt.egg-info/top_level.txt
django_alt/abstract/__init__.py
django_alt/abstract/endpoints.py
django_alt/abstract/serializers.py
django_alt/abstract/validators.py
django_alt/utils/__init__.py
django_alt/utils/functional.py
django_alt/utils/permissions.py
django_alt/utils/shortcuts.py
django_alt_tests/__init__.py
django_alt_tests/manage.py
django_alt_tests/conf/__init__.py
django_alt_tests/conf/endpoints.py
django_alt_tests/conf/models.py
django_alt_tests/conf/settings.py
django_alt_tests/conf/urls.py
django_alt_tests/conf/wsgi.py
django_alt_tests/conf/migrations/0001_initial.py
django_alt_tests/conf/migrations/__init__.py
django_alt_tests/tests/__init__.py
django_alt_tests/tests/test_ddict.py
django_alt_tests/tests/test_endpoints.py
django_alt_tests/tests/test_serializers.py
django_alt_tests/tests/test_shortcuts.py
django_alt_tests/tests/test_validators.py