Metadata-Version: 1.0
Name: django-alt
Version: 0.74
Summary: Alternative approach to data validation and REST endpoints in Django and DRF
Home-page: https://github.com/poskadesign/django-alt
Author: Vilius Poška
Author-email: vilius@poska.lt
License: MIT
Platform: UNKNOWN
